readline.py
pyreadline/__init__.py
pyreadline/rlmain.py
pyreadline/error.py
pyreadline/logserver.py
pyreadline/unicode_helper.py
pyreadline/get_doc.py
pyreadline/release.py
pyreadline/py3k_compat.py
pyreadline/logger.py
pyreadline/clipboard/__init__.py
pyreadline/clipboard/win32_clipboard.py
pyreadline/clipboard/no_clipboard.py
pyreadline/clipboard/ironpython_clipboard.py
pyreadline/console/__init__.py
pyreadline/console/consolebase.py
pyreadline/console/console_attributes.py
pyreadline/console/ansi.py
pyreadline/console/console.py
pyreadline/console/ironpython_console.py
pyreadline/console/event.py
pyreadline/configuration/pyreadlineconfig.ini
pyreadline/configuration/startup.py
pyreadline/keysyms/__init__.py
pyreadline/keysyms/winconstants.py
pyreadline/keysyms/ironpython_keysyms.py
pyreadline/keysyms/keysyms.py
pyreadline/keysyms/common.py
pyreadline/test/__init__.py
pyreadline/test/test_emacs.py
pyreadline/test/test_lineeditor.py
pyreadline/test/common.py
pyreadline/test/test_vi.py
pyreadline/test/test_history.py
pyreadline/lineeditor/__init__.py
pyreadline/lineeditor/wordmatcher.py
pyreadline/lineeditor/lineobj.py
pyreadline/lineeditor/history.py
pyreadline/modes/__init__.py
pyreadline/modes/basemode.py
pyreadline/modes/notemacs.py
pyreadline/modes/emacs.py
pyreadline/modes/vi.py
pyreadline_ais-2.0.3.dist-info/DESCRIPTION.rst
pyreadline_ais-2.0.3.dist-info/metadata.json
pyreadline_ais-2.0.3.dist-info/WHEEL
pyreadline_ais-2.0.3.dist-info/METADATA
pyreadline_ais-2.0.3.dist-info/top_level.txt
pyreadline_ais-2.0.3.dist-info/RECORD
