Metadata-Version: 2.0
Name: pyreadline-ais
Version: 2.0.3
Summary: A python implmementation of GNU readline.
Home-page: https://github.com/ainfosec/pyreadline
Author: Adam Meily
Author-email: meilya@ainfosec.com
License: BSD
Download-URL: https://pypi.python.org/pypi/pyreadline-ais/
Keywords: readline,pyreadline
Platform: Windows XP/2000/NT
Platform: Windows 95/98/ME
Classifier: Development Status :: 5 - Production/Stable
Classifier: Environment :: Console
Classifier: Operating System :: Microsoft :: Windows
Classifier: License :: OSI Approved :: BSD License
Classifier: Programming Language :: Python :: 2.6
Classifier: Programming Language :: Python :: 2.7
Classifier: Programming Language :: Python :: 3.2
Classifier: Programming Language :: Python :: 3.3
